coordinate_converter/__init__.py
coordinate_converter/coordinate_converter.py
coordinateconverter-0.3.dist-info/METADATA
coordinateconverter-0.3.dist-info/WHEEL
coordinateconverter-0.3.dist-info/top_level.txt
coordinateconverter-0.3.dist-info/RECORD
