Metadata-Version: 2.2
Name: coordinateConverter
Version: 0.3
Requires-Dist: pyproj
Dynamic: requires-dist
